test0000001/__init__.py
test0000001/steps.py
test0000001-3.0.2.dist-info/METADATA
test0000001-3.0.2.dist-info/WHEEL
test0000001-3.0.2.dist-info/entry_points.txt
test0000001-3.0.2.dist-info/top_level.txt
test0000001-3.0.2.dist-info/RECORD
