Metadata-Version: 2.1
Name: test0000001
Version: 3.0.2
Summary: UNKNOWN
Home-page: UNKNOWN
License: UNKNOWN
Platform: UNKNOWN
Requires-Dist: pyrebase
Requires-Dist: uuid
Requires-Dist: python-dotenv
